sbc_gpio/DIR.py
sbc_gpio/EVENT.py
sbc_gpio/PULL.py
sbc_gpio/__init__.py
sbc_gpio/__main__.py
sbc_gpio/dynamic_dts.py
sbc_gpio/scripts.py
sbc_gpio/device_tests/_test_base.py
sbc_gpio/device_tests/bmx_spi.py
sbc_gpio/device_tests/button_gpiod.py
sbc_gpio/device_tests/dht_spi.py
sbc_gpio/device_tests/i2c_display.py
sbc_gpio/device_tests/ir.py
sbc_gpio/device_tests/led_gpiod.py
sbc_gpio/device_tests/uart.py
sbc_gpio/gpio_libs/_generic_gpio.py
sbc_gpio/gpio_libs/gpiod.py
sbc_gpio/gpio_libs/rpi_gpio.py
sbc_gpio/platforms/_generic.py
sbc_gpio/platforms/pi4b.py
sbc_gpio/platforms/rock5b.py
sbc_gpio/tests/devtester_test.py
sbc_gpio/tests/sbc_test.py
sbc_gpio/tests/test_dynamic_overlay.py
sbc_gpio-1.0.3.dist-info/LICENSE
sbc_gpio-1.0.3.dist-info/METADATA
sbc_gpio-1.0.3.dist-info/WHEEL
sbc_gpio-1.0.3.dist-info/entry_points.txt
sbc_gpio-1.0.3.dist-info/top_level.txt
sbc_gpio-1.0.3.dist-info/RECORD
